<?xml version="1.0" encoding="utf-8"?>
<modification>
    <name>Orders To Excel</name>
    <code>orders_to_excel</code>
    <version>1.0</version>
    <author>Zamkovsky</author>
    <link></link>
    <file path="admin/view/template/sale/order_list.tpl">
        <operation>
            <search><![CDATA[<button type="button" id="button-filter" class="btn btn-primary pull-right"><i class="fa fa-filter"></i> <?php echo $button_filter; ?></button>]]></search>
            <add position="after"><![CDATA[
            test123
            ]]></add>
        </operation>
    </file>  
</modification>